{
    "code": 200,
    "msg": "AZi5qQlA7E",
    "result": {
        "id": 87596,
        "name": "BYlT8Bjzlu",
        "tag": "少女系,萌神,萝莉,未来日记",
        "coverId": 88492,
        "coverUrl": "http://via.placeholder.com/102x158",
        "pictures": [
            {
                "id": 88562,
                "name": "h2rUC99BI2",
                "url": "http://via.placeholder.com/100x140",
                "position": 59172,
                "worksId": 89163,
                "creatorId": 89625,
                "createTime": 1529678522998,
                "updateTime": 1529676535757
            },
            {
                "id": 89834,
                "name": "W5k6YHwdVf",
                "url": "http://via.placeholder.com/100x140",
                "position": 51438,
                "worksId": 90130,
                "creatorId": 90551,
                "createTime": 1529678675186,
                "updateTime": 1529676864855
            },
            {
                "id": 91355,
                "name": "sFWfhqBeec",
                "url": "http://via.placeholder.com/100x140",
                "position": 80238,
                "worksId": 91972,
                "creatorId": 92379,
                "createTime": 1529677158809,
                "updateTime": 1529677794538
            }
        ],
        "category": 1,
        "description": "dHkrzqQNQI",
        "privilege": 0,
        "authorization": 1,
        "createTime": 1529677389715,
        "updateTime": 1529678304008
    }
}